cardutil/BitArray.py
cardutil/__init__.py
cardutil/card.py
cardutil/config.py
cardutil/iso8583.py
cardutil/key.py
cardutil/mciipm.py
cardutil/pinblock.py
cardutil/cli/__init__.py
cardutil/cli/mci_csv_to_ipm.py
cardutil/cli/mci_ipm_encode.py
cardutil/cli/mci_ipm_param_encode.py
cardutil/cli/mci_ipm_param_to_csv.py
cardutil/cli/mci_ipm_to_csv.py
cardutil/cli/mideu.py
cardutil/cli/paramconv.py
cardutil/vendor/__init__.py
cardutil/vendor/hexdump.py
cardutil-0.7.2.dist-info/licenses/LICENSE
cardutil-0.7.2.dist-info/METADATA
cardutil-0.7.2.dist-info/WHEEL
cardutil-0.7.2.dist-info/entry_points.txt
cardutil-0.7.2.dist-info/top_level.txt
cardutil-0.7.2.dist-info/RECORD
