Metadata-Version: 2.4
Name: cardutil
Version: 0.7.2
Summary: Python package for working with payment card systems
Author-email: Anthony Delosa <adelosa@gmail.com>
License-Expression: MIT
Project-URL: Homepage, https://github.com/adelosa/cardutil
Classifier: Programming Language :: Python :: 3
Classifier: Programming Language :: Python :: 3.9
Classifier: Programming Language :: Python :: 3.10
Classifier: Programming Language :: Python :: 3.11
Classifier: Programming Language :: Python :: 3.12
Classifier: Programming Language :: Python :: 3.13
Requires-Python: >=3.9
License-File: LICENSE
Provides-Extra: docs
Requires-Dist: sphinx; extra == "docs"
Requires-Dist: sphinx_rtd_theme; extra == "docs"
Requires-Dist: cryptography>=44; extra == "docs"
Provides-Extra: test
Requires-Dist: flake8; extra == "test"
Requires-Dist: pytest; extra == "test"
Requires-Dist: bump2version; extra == "test"
Requires-Dist: coverage; extra == "test"
Requires-Dist: cryptography; extra == "test"
Requires-Dist: python-dateutil; extra == "test"
Provides-Extra: crypto
Requires-Dist: cryptography>=44; extra == "crypto"
Dynamic: license-file
